uchroot/__init__.py
uchroot/__main__.py
uchroot/dump_constants.py
uchroot-0.1.4.dist-info/LICENSE
uchroot-0.1.4.dist-info/METADATA
uchroot-0.1.4.dist-info/WHEEL
uchroot-0.1.4.dist-info/entry_points.txt
uchroot-0.1.4.dist-info/top_level.txt
uchroot-0.1.4.dist-info/RECORD
