Metadata-Version: 2.1
Name: uchroot
Version: 0.1.4
Summary: chroot without root
Home-page: https://github.com/cheshirekow/uchroot
Author: Josh Bialkowski
Author-email: josh.bialkowski@gmail.com
License: UNKNOWN
Download-URL: https://github.com/cheshirekow/uchroot/archive/0.1.4.tar.gz
Keywords: chroot,linux
Platform: UNKNOWN
